{
  "01": "10",
  "02": "10",
  "04": "10",
  "06": "20",
  "08": "20",
  "10": "25",
  "11": "20",
  "12": "25",
  "14": "20",
  "15": "30",
  "17": "20",
  "19": "30",
  "20": "25",
  "22": "30",
  "24": "25",
  "25": "25",
  "26": "30",
  "27": "30",
  "30": "20",
  "31": "10",
  "33": "10",
  "34": "15",
  "35": "20",
  "36": "10",
  "37": "10",
  "38": "15",
  "40": "10",
  "42": "15",
  "44": "20",
  "45": "10",
  "46": "10",
  "48": "15",
  "49": "10",
  "51": "20",
  "52": "10",
  "54": "10",
  "56": "15",
  "58": "20",
  "60": "15",
  "62": "15",
  "64": "10",
  "66": "10",
  "67": "15",
  "68": "10",
  "70": "15",
  "72": "10",
  "74": "15",
  "75": "10",
  "77": "15",
  "79": "20",
  "80": "10",
  "82": "15",
  "83": "20",
  "84": "20",
  "86": "20",
  "87": "20",
  "89": "20",
  "91": "20",
  "92": "10",
  "93": "20",
  "94": "10",
  "95": "15",
  "96": "15"
}
